easy_tree_maker/__init__.py
easy_tree_maker/cli.py
easy_tree_maker/core.py
tests/__init__.py
tests/test_core.py
easy_tree_maker-0.1.6.dist-info/METADATA
easy_tree_maker-0.1.6.dist-info/WHEEL
easy_tree_maker-0.1.6.dist-info/entry_points.txt
easy_tree_maker-0.1.6.dist-info/top_level.txt
easy_tree_maker-0.1.6.dist-info/RECORD
