Metadata-Version: 2.1
Name: easy-tree-maker
Version: 0.1.6
Summary: A tool to create a directory and file structure from JSON or Python object
Home-page: https://github.com/MahrezBH/easy_tree_maker
Author: Mahrez BENHAMAD
Author-email: contact@mahrezbenhamad.com
Classifier: Programming Language :: Python :: 3
Classifier: License :: OSI Approved :: MIT License
Classifier: Operating System :: OS Independent
Requires-Python: >=3.6
